<?xml version="1.0" ?>
<annotation>
	<folder>none</folder>
	<filename>16908.jpg</filename>
	<source>201908</source>
	<owner>halftop</owner>
	<size>
		<width>2048</width>
		<height>2048</height>
		<depth>3</depth>
	</size>
	<segmented>0</segmented>
	<object>
		<name>pn</name>
		<pose>Unspecified</pose>
		<truncated>0</truncated>
		<difficult>0</difficult>
		<bndbox>
			<xmin>1112</xmin>
			<ymin>958</ymin>
			<xmax>1136</xmax>
			<ymax>991</ymax>
		</bndbox>
	</object>
	<object>
		<name>p11</name>
		<pose>Unspecified</pose>
		<truncated>0</truncated>
		<difficult>0</difficult>
		<bndbox>
			<xmin>1794</xmin>
			<ymin>847</ymin>
			<xmax>1820</xmax>
			<ymax>888</ymax>
		</bndbox>
	</object>
	<object>
		<name>pm10</name>
		<pose>Unspecified</pose>
		<truncated>0</truncated>
		<difficult>0</difficult>
		<bndbox>
			<xmin>1795</xmin>
			<ymin>892</ymin>
			<xmax>1828</xmax>
			<ymax>928</ymax>
		</bndbox>
	</object>
</annotation>
