<?xml version="1.0" ?>
<annotation>
	<folder>none</folder>
	<filename>21882.jpg</filename>
	<source>201908</source>
	<owner>halftop</owner>
	<size>
		<width>2048</width>
		<height>2048</height>
		<depth>3</depth>
	</size>
	<segmented>0</segmented>
	<object>
		<name>p26</name>
		<pose>Unspecified</pose>
		<truncated>0</truncated>
		<difficult>0</difficult>
		<bndbox>
			<xmin>1279</xmin>
			<ymin>531</ymin>
			<xmax>1381</xmax>
			<ymax>630</ymax>
		</bndbox>
	</object>
	<object>
		<name>po</name>
		<pose>Unspecified</pose>
		<truncated>0</truncated>
		<difficult>0</difficult>
		<bndbox>
			<xmin>1411</xmin>
			<ymin>549</ymin>
			<xmax>1506</xmax>
			<ymax>645</ymax>
		</bndbox>
	</object>
	<object>
		<name>p9</name>
		<pose>Unspecified</pose>
		<truncated>0</truncated>
		<difficult>0</difficult>
		<bndbox>
			<xmin>1531</xmin>
			<ymin>566</ymin>
			<xmax>1621</xmax>
			<ymax>658</ymax>
		</bndbox>
	</object>
</annotation>
