<?xml version="1.0" ?>
<annotation>
	<folder>none</folder>
	<filename>54982.jpg</filename>
	<source>201908</source>
	<owner>halftop</owner>
	<size>
		<width>2048</width>
		<height>2048</height>
		<depth>3</depth>
	</size>
	<segmented>0</segmented>
	<object>
		<name>pl40</name>
		<pose>Unspecified</pose>
		<truncated>0</truncated>
		<difficult>0</difficult>
		<bndbox>
			<xmin>171</xmin>
			<ymin>887</ymin>
			<xmax>190</xmax>
			<ymax>917</ymax>
		</bndbox>
	</object>
	<object>
		<name>pn</name>
		<pose>Unspecified</pose>
		<truncated>0</truncated>
		<difficult>0</difficult>
		<bndbox>
			<xmin>190</xmin>
			<ymin>887</ymin>
			<xmax>211</xmax>
			<ymax>914</ymax>
		</bndbox>
	</object>
</annotation>
