<?xml version="1.0" ?>
<annotation>
	<folder>none</folder>
	<filename>58753.jpg</filename>
	<source>201908</source>
	<owner>halftop</owner>
	<size>
		<width>2048</width>
		<height>2048</height>
		<depth>3</depth>
	</size>
	<segmented>0</segmented>
	<object>
		<name>pne</name>
		<pose>Unspecified</pose>
		<truncated>0</truncated>
		<difficult>0</difficult>
		<bndbox>
			<xmin>1763</xmin>
			<ymin>930</ymin>
			<xmax>1779</xmax>
			<ymax>956</ymax>
		</bndbox>
	</object>
	<object>
		<name>i4</name>
		<pose>Unspecified</pose>
		<truncated>0</truncated>
		<difficult>0</difficult>
		<bndbox>
			<xmin>1840</xmin>
			<ymin>933</ymin>
			<xmax>1855</xmax>
			<ymax>957</ymax>
		</bndbox>
	</object>
	<object>
		<name>io</name>
		<pose>Unspecified</pose>
		<truncated>0</truncated>
		<difficult>0</difficult>
		<bndbox>
			<xmin>314</xmin>
			<ymin>887</ymin>
			<xmax>341</xmax>
			<ymax>947</ymax>
		</bndbox>
	</object>
	<object>
		<name>io</name>
		<pose>Unspecified</pose>
		<truncated>0</truncated>
		<difficult>0</difficult>
		<bndbox>
			<xmin>313</xmin>
			<ymin>955</ymin>
			<xmax>339</xmax>
			<ymax>1014</ymax>
		</bndbox>
	</object>
	<object>
		<name>pn</name>
		<pose>Unspecified</pose>
		<truncated>0</truncated>
		<difficult>0</difficult>
		<bndbox>
			<xmin>524</xmin>
			<ymin>815</ymin>
			<xmax>540</xmax>
			<ymax>858</ymax>
		</bndbox>
	</object>
</annotation>
