<?xml version="1.0" ?>
<annotation>
	<folder>none</folder>
	<filename>61276.jpg</filename>
	<source>201908</source>
	<owner>halftop</owner>
	<size>
		<width>2048</width>
		<height>2048</height>
		<depth>3</depth>
	</size>
	<segmented>0</segmented>
	<object>
		<name>pl30</name>
		<pose>Unspecified</pose>
		<truncated>0</truncated>
		<difficult>0</difficult>
		<bndbox>
			<xmin>1968</xmin>
			<ymin>869</ymin>
			<xmax>2009</xmax>
			<ymax>925</ymax>
		</bndbox>
	</object>
	<object>
		<name>w55</name>
		<pose>Unspecified</pose>
		<truncated>0</truncated>
		<difficult>0</difficult>
		<bndbox>
			<xmin>1967</xmin>
			<ymin>983</ymin>
			<xmax>2010</xmax>
			<ymax>1033</ymax>
		</bndbox>
	</object>
	<object>
		<name>pl50</name>
		<pose>Unspecified</pose>
		<truncated>0</truncated>
		<difficult>0</difficult>
		<bndbox>
			<xmin>1072</xmin>
			<ymin>963</ymin>
			<xmax>1085</xmax>
			<ymax>976</ymax>
		</bndbox>
	</object>
	<object>
		<name>pn</name>
		<pose>Unspecified</pose>
		<truncated>0</truncated>
		<difficult>0</difficult>
		<bndbox>
			<xmin>1085</xmin>
			<ymin>961</ymin>
			<xmax>1100</xmax>
			<ymax>976</ymax>
		</bndbox>
	</object>
</annotation>
