<?xml version="1.0" ?>
<annotation>
	<folder>none</folder>
	<filename>61606.jpg</filename>
	<source>201908</source>
	<owner>halftop</owner>
	<size>
		<width>2048</width>
		<height>2048</height>
		<depth>3</depth>
	</size>
	<segmented>0</segmented>
	<object>
		<name>pn</name>
		<pose>Unspecified</pose>
		<truncated>0</truncated>
		<difficult>0</difficult>
		<bndbox>
			<xmin>1203</xmin>
			<ymin>883</ymin>
			<xmax>1229</xmax>
			<ymax>909</ymax>
		</bndbox>
	</object>
	<object>
		<name>pl80</name>
		<pose>Unspecified</pose>
		<truncated>0</truncated>
		<difficult>0</difficult>
		<bndbox>
			<xmin>1176</xmin>
			<ymin>883</ymin>
			<xmax>1201</xmax>
			<ymax>909</ymax>
		</bndbox>
	</object>
</annotation>
