<?xml version="1.0" ?>
<annotation>
	<folder>none</folder>
	<filename>74821.jpg</filename>
	<source>201908</source>
	<owner>halftop</owner>
	<size>
		<width>2048</width>
		<height>2048</height>
		<depth>3</depth>
	</size>
	<segmented>0</segmented>
	<object>
		<name>pl80</name>
		<pose>Unspecified</pose>
		<truncated>0</truncated>
		<difficult>0</difficult>
		<bndbox>
			<xmin>572</xmin>
			<ymin>816</ymin>
			<xmax>616</xmax>
			<ymax>861</ymax>
		</bndbox>
	</object>
	<object>
		<name>il60</name>
		<pose>Unspecified</pose>
		<truncated>0</truncated>
		<difficult>0</difficult>
		<bndbox>
			<xmin>664</xmin>
			<ymin>808</ymin>
			<xmax>712</xmax>
			<ymax>856</ymax>
		</bndbox>
	</object>
	<object>
		<name>pl80</name>
		<pose>Unspecified</pose>
		<truncated>0</truncated>
		<difficult>0</difficult>
		<bndbox>
			<xmin>754</xmin>
			<ymin>804</ymin>
			<xmax>801</xmax>
			<ymax>846</ymax>
		</bndbox>
	</object>
	<object>
		<name>il60</name>
		<pose>Unspecified</pose>
		<truncated>0</truncated>
		<difficult>0</difficult>
		<bndbox>
			<xmin>856</xmin>
			<ymin>794</ymin>
			<xmax>905</xmax>
			<ymax>844</ymax>
		</bndbox>
	</object>
	<object>
		<name>pl80</name>
		<pose>Unspecified</pose>
		<truncated>0</truncated>
		<difficult>0</difficult>
		<bndbox>
			<xmin>962</xmin>
			<ymin>792</ymin>
			<xmax>1009</xmax>
			<ymax>837</ymax>
		</bndbox>
	</object>
	<object>
		<name>il50</name>
		<pose>Unspecified</pose>
		<truncated>0</truncated>
		<difficult>0</difficult>
		<bndbox>
			<xmin>1066</xmin>
			<ymin>788</ymin>
			<xmax>1113</xmax>
			<ymax>833</ymax>
		</bndbox>
	</object>
	<object>
		<name>pl80</name>
		<pose>Unspecified</pose>
		<truncated>0</truncated>
		<difficult>0</difficult>
		<bndbox>
			<xmin>1158</xmin>
			<ymin>784</ymin>
			<xmax>1205</xmax>
			<ymax>830</ymax>
		</bndbox>
	</object>
	<object>
		<name>il50</name>
		<pose>Unspecified</pose>
		<truncated>0</truncated>
		<difficult>0</difficult>
		<bndbox>
			<xmin>1257</xmin>
			<ymin>784</ymin>
			<xmax>1308</xmax>
			<ymax>829</ymax>
		</bndbox>
	</object>
</annotation>
