<?xml version="1.0" ?>
<annotation>
	<folder>none</folder>
	<filename>78170.jpg</filename>
	<source>201908</source>
	<owner>halftop</owner>
	<size>
		<width>2048</width>
		<height>2048</height>
		<depth>3</depth>
	</size>
	<segmented>0</segmented>
	<object>
		<name>i5</name>
		<pose>Unspecified</pose>
		<truncated>0</truncated>
		<difficult>0</difficult>
		<bndbox>
			<xmin>835</xmin>
			<ymin>996</ymin>
			<xmax>865</xmax>
			<ymax>1027</ymax>
		</bndbox>
	</object>
	<object>
		<name>pl60</name>
		<pose>Unspecified</pose>
		<truncated>0</truncated>
		<difficult>0</difficult>
		<bndbox>
			<xmin>1226</xmin>
			<ymin>860</ymin>
			<xmax>1270</xmax>
			<ymax>908</ymax>
		</bndbox>
	</object>
	<object>
		<name>pn</name>
		<pose>Unspecified</pose>
		<truncated>0</truncated>
		<difficult>0</difficult>
		<bndbox>
			<xmin>1282</xmin>
			<ymin>863</ymin>
			<xmax>1327</xmax>
			<ymax>908</ymax>
		</bndbox>
	</object>
	<object>
		<name>i4</name>
		<pose>Unspecified</pose>
		<truncated>0</truncated>
		<difficult>0</difficult>
		<bndbox>
			<xmin>1328</xmin>
			<ymin>864</ymin>
			<xmax>1371</xmax>
			<ymax>912</ymax>
		</bndbox>
	</object>
	<object>
		<name>i2</name>
		<pose>Unspecified</pose>
		<truncated>0</truncated>
		<difficult>0</difficult>
		<bndbox>
			<xmin>1440</xmin>
			<ymin>868</ymin>
			<xmax>1478</xmax>
			<ymax>911</ymax>
		</bndbox>
	</object>
	<object>
		<name>pr50</name>
		<pose>Unspecified</pose>
		<truncated>0</truncated>
		<difficult>0</difficult>
		<bndbox>
			<xmin>1486</xmin>
			<ymin>966</ymin>
			<xmax>1536</xmax>
			<ymax>1018</ymax>
		</bndbox>
	</object>
</annotation>
